{
"meta":{"test_sets":[],"test_metrics":[],"learn_metrics":[{"best_value":"Min","name":"RMSE"}],"launch_mode":"Train","parameters":"","iteration_count":100,"learn_sets":["learn"],"name":"experiment"},
"iterations":[
{"learn":[14.84063055],"iteration":0,"passed_time":0.0007901399026,"remaining_time":0.07822385035},
{"learn":[14.0277146],"iteration":1,"passed_time":0.002072330079,"remaining_time":0.1015441739},
{"learn":[13.28168108],"iteration":2,"passed_time":0.002855060823,"remaining_time":0.09231363328},
{"learn":[12.67295736],"iteration":3,"passed_time":0.003705115218,"remaining_time":0.08892276524},
{"learn":[12.13118282],"iteration":4,"passed_time":0.00448576699,"remaining_time":0.0852295728},
{"learn":[11.64284615],"iteration":5,"passed_time":0.005233004909,"remaining_time":0.08198374358},
{"learn":[11.17583451],"iteration":6,"passed_time":0.005997540885,"remaining_time":0.07968161461},
{"learn":[10.70698042],"iteration":7,"passed_time":0.006768970032,"remaining_time":0.07784315537},
{"learn":[10.30261074],"iteration":8,"passed_time":0.007498959993,"remaining_time":0.0758228177},
{"learn":[9.897928797],"iteration":9,"passed_time":0.008353262505,"remaining_time":0.07517936255},
{"learn":[9.43818595],"iteration":10,"passed_time":0.009138773563,"remaining_time":0.0739409861},
{"learn":[9.067087678],"iteration":11,"passed_time":0.009828967475,"remaining_time":0.07207909482},
{"learn":[8.769647814],"iteration":12,"passed_time":0.01064311826,"remaining_time":0.07122702221},
{"learn":[8.494260327],"iteration":13,"passed_time":0.01138718512,"remaining_time":0.06994985146},
{"learn":[8.18170444],"iteration":14,"passed_time":0.01208199285,"remaining_time":0.06846462615},
{"learn":[7.872819124],"iteration":15,"passed_time":0.01280070125,"remaining_time":0.06720368158},
{"learn":[7.637017332],"iteration":16,"passed_time":0.01352285123,"remaining_time":0.06602333248},
{"learn":[7.415872705],"iteration":17,"passed_time":0.01427999308,"remaining_time":0.06505330179},
{"learn":[7.161020449],"iteration":18,"passed_time":0.01497812716,"remaining_time":0.06385412106},
{"learn":[6.971236341],"iteration":19,"passed_time":0.01567696259,"remaining_time":0.06270785035},
{"learn":[6.841615556],"iteration":20,"passed_time":0.01649476535,"remaining_time":0.06205173633},
{"learn":[6.687931434],"iteration":21,"passed_time":0.01728256078,"remaining_time":0.06127453366},
{"learn":[6.508058838],"iteration":22,"passed_time":0.018015827,"remaining_time":0.0603138556},
{"learn":[6.348045518],"iteration":23,"passed_time":0.01892609646,"remaining_time":0.05993263878},
{"learn":[6.190854657],"iteration":24,"passed_time":0.01957477103,"remaining_time":0.05872431309},
{"learn":[6.083848414],"iteration":25,"passed_time":0.020233074,"remaining_time":0.05758644139},
{"learn":[5.948861607],"iteration":26,"passed_time":0.02089134692,"remaining_time":0.05648401203},
{"learn":[5.820594273],"iteration":27,"passed_time":0.02148156979,"remaining_time":0.05523832232},
{"learn":[5.718358733],"iteration":28,"passed_time":0.02213291446,"remaining_time":0.05418748024},
{"learn":[5.62831756],"iteration":29,"passed_time":0.02284681368,"remaining_time":0.05330923191},
{"learn":[5.501668539],"iteration":30,"passed_time":0.02345812685,"remaining_time":0.05221325009},
{"learn":[5.404367962],"iteration":31,"passed_time":0.02406458074,"remaining_time":0.05113723408},
{"learn":[5.312889065],"iteration":32,"passed_time":0.02467311361,"remaining_time":0.05009389733},
{"learn":[5.220401854],"iteration":33,"passed_time":0.02527041501,"remaining_time":0.04905433502},
{"learn":[5.130160358],"iteration":34,"passed_time":0.02585721635,"remaining_time":0.04802054464},
{"learn":[5.056241699],"iteration":35,"passed_time":0.02643933874,"remaining_time":0.04700326888},
{"learn":[4.971821431],"iteration":36,"passed_time":0.02699042182,"remaining_time":0.04595666419},
{"learn":[4.90630594],"iteration":37,"passed_time":0.02765955048,"remaining_time":0.04512874026},
{"learn":[4.847558899],"iteration":38,"passed_time":0.0282653882,"remaining_time":0.04420996615},
{"learn":[4.795388439],"iteration":39,"passed_time":0.02882254288,"remaining_time":0.04323381432},
{"learn":[4.763423781],"iteration":40,"passed_time":0.02943409151,"remaining_time":0.04235637558},
{"learn":[4.718909606],"iteration":41,"passed_time":0.03002116336,"remaining_time":0.04145779702},
{"learn":[4.660496339],"iteration":42,"passed_time":0.03061453726,"remaining_time":0.04058206102},
{"learn":[4.619083415],"iteration":43,"passed_time":0.03120348269,"remaining_time":0.03971352343},
{"learn":[4.578792627],"iteration":44,"passed_time":0.03177840132,"remaining_time":0.03884026828},
{"learn":[4.53420217],"iteration":45,"passed_time":0.03260274191,"remaining_time":0.03827278398},
{"learn":[4.480755407],"iteration":46,"passed_time":0.03337444158,"remaining_time":0.03763500859},
{"learn":[4.440459443],"iteration":47,"passed_time":0.03404928115,"remaining_time":0.03688672124},
{"learn":[4.399489675],"iteration":48,"passed_time":0.03463673373,"remaining_time":0.03605047796},
{"learn":[4.351777663],"iteration":49,"passed_time":0.03520892715,"remaining_time":0.03520892715},
{"learn":[4.322290972],"iteration":50,"passed_time":0.0358117491,"remaining_time":0.03440736678},
{"learn":[4.294233013],"iteration":51,"passed_time":0.03646194658,"remaining_time":0.03365718146},
{"learn":[4.275623532],"iteration":52,"passed_time":0.03709534196,"remaining_time":0.03289586928},
{"learn":[4.237862852],"iteration":53,"passed_time":0.03768601069,"remaining_time":0.03210289799},
{"learn":[4.20766476],"iteration":54,"passed_time":0.03826867412,"remaining_time":0.03131073337},
{"learn":[4.188319833],"iteration":55,"passed_time":0.03884568675,"remaining_time":0.03052161102},
{"learn":[4.150006672],"iteration":56,"passed_time":0.03944807787,"remaining_time":0.02975907629},
{"learn":[4.109226526],"iteration":57,"passed_time":0.04000711616,"remaining_time":0.02897067032},
{"learn":[4.077151393],"iteration":58,"passed_time":0.04056679567,"remaining_time":0.02819048512},
{"learn":[4.043789762],"iteration":59,"passed_time":0.04115667288,"remaining_time":0.02743778192},
{"learn":[4.035036878],"iteration":60,"passed_time":0.04165823132,"remaining_time":0.02663395117},
{"learn":[4.013853126],"iteration":61,"passed_time":0.04225084377,"remaining_time":0.02589567844},
{"learn":[3.979587038],"iteration":62,"passed_time":0.04283632258,"remaining_time":0.02515784024},
{"learn":[3.950449041],"iteration":63,"passed_time":0.04339687375,"remaining_time":0.02441074148},
{"learn":[3.941048557],"iteration":64,"passed_time":0.04388426512,"remaining_time":0.02362998891},
{"learn":[3.919502044],"iteration":65,"passed_time":0.04444669989,"remaining_time":0.02289678479},
{"learn":[3.908419086],"iteration":66,"passed_time":0.0450521168,"remaining_time":0.02218984858},
{"learn":[3.883974731],"iteration":67,"passed_time":0.04561796811,"remaining_time":0.02146727911},
{"learn":[3.862579573],"iteration":68,"passed_time":0.04621049572,"remaining_time":0.02076123721},
{"learn":[3.849836895],"iteration":69,"passed_time":0.04680746649,"remaining_time":0.02006034278},
{"learn":[3.824998864],"iteration":70,"passed_time":0.04746461225,"remaining_time":0.0193869543},
{"learn":[3.791315502],"iteration":71,"passed_time":0.04817547032,"remaining_time":0.01873490512},
{"learn":[3.758805858],"iteration":72,"passed_time":0.04876380458,"remaining_time":0.01803592772},
{"learn":[3.739757196],"iteration":73,"passed_time":0.04935959309,"remaining_time":0.01734255974},
{"learn":[3.727492189],"iteration":74,"passed_time":0.04995719507,"remaining_time":0.01665239836},
{"learn":[3.706251604],"iteration":75,"passed_time":0.05055548837,"remaining_time":0.01596489106},
{"learn":[3.685860196],"iteration":76,"passed_time":0.05114653782,"remaining_time":0.01527753727},
{"learn":[3.663779561],"iteration":77,"passed_time":0.05173157579,"remaining_time":0.01459095727},
{"learn":[3.648059878],"iteration":78,"passed_time":0.05230314802,"remaining_time":0.01390336846},
{"learn":[3.643276906],"iteration":79,"passed_time":0.05289476857,"remaining_time":0.01322369214},
{"learn":[3.638022193],"iteration":80,"passed_time":0.05346182217,"remaining_time":0.01254042742},
{"learn":[3.625433746],"iteration":81,"passed_time":0.05412966337,"remaining_time":0.01188212123},
{"learn":[3.596253585],"iteration":82,"passed_time":0.05474228939,"remaining_time":0.01121227614},
{"learn":[3.571081695],"iteration":83,"passed_time":0.05533325869,"remaining_time":0.01053966832},
{"learn":[3.56195045],"iteration":84,"passed_time":0.05591652326,"remaining_time":0.009867621753},
{"learn":[3.518241793],"iteration":85,"passed_time":0.0565453449,"remaining_time":0.009205056146},
{"learn":[3.494336727],"iteration":86,"passed_time":0.05714859767,"remaining_time":0.008539445629},
{"learn":[3.478022077],"iteration":87,"passed_time":0.05770749569,"remaining_time":0.007869203958},
{"learn":[3.450668514],"iteration":88,"passed_time":0.05827280596,"remaining_time":0.007202256916},
{"learn":[3.419074933],"iteration":89,"passed_time":0.05886435637,"remaining_time":0.006540484041},
{"learn":[3.376901598],"iteration":90,"passed_time":0.05943952548,"remaining_time":0.005878634388},
{"learn":[3.365852239],"iteration":91,"passed_time":0.06001685872,"remaining_time":0.00521885728},
{"learn":[3.34189864],"iteration":92,"passed_time":0.06057831162,"remaining_time":0.004559657864},
{"learn":[3.320205229],"iteration":93,"passed_time":0.06120160269,"remaining_time":0.003906485278},
{"learn":[3.307646434],"iteration":94,"passed_time":0.06179557773,"remaining_time":0.003252398828},
{"learn":[3.304337773],"iteration":95,"passed_time":0.06256170642,"remaining_time":0.002606737767},
{"learn":[3.28404604],"iteration":96,"passed_time":0.06321608656,"remaining_time":0.001955136698},
{"learn":[3.262609827],"iteration":97,"passed_time":0.06381004156,"remaining_time":0.001302245746},
{"learn":[3.252134778],"iteration":98,"passed_time":0.06440120123,"remaining_time":0.0006505171841},
{"learn":[3.245174796],"iteration":99,"passed_time":0.06500101744,"remaining_time":0}
]}